{"number": 7, "target": "seals", "target_context": "seven seals in a seal sanctuary\n", "image_url": "https://image.shutterstock.com/image-photo/seven-seals-seal-sanctuary-600w-3283098.jpg", "dataset_name": "conceptual_12m-train", "org_id": 8447823, "image": {"_type": "image-file", "sha256": "1ef918138f60830383a26b6bc16e8ffaed1fdd2afdb508b6d897a34eeef7c4b5", "size": 367176, "path": "media/images/image_0_1ef918138f60830383a2.png", "format": "png", "width": 600, "height": 420, "caption": "seven seals in a seal sanctuary\n"}, "reviewed": true, "_timestamp": 1716323481.803424, "_runtime": 2.4036197662353516, "_step": 0, "_wandb": {"runtime": 1}}