{"number": 6, "target": "colors", "target_context": "the webster mesh home office chairs are available in six colors", "image_url": "https://www.harveynorman.com.au/blog/assets/Webster-Chairs-1000x812.jpg", "dataset_name": "conceptual_12m-train", "org_id": 12108471, "image": {"_type": "image-file", "sha256": "d63558f12924665a5b56cadb81988fb465c4b36be6781ff1cc1327a547573ed1", "size": 373179, "path": "media/images/image_0_d63558f12924665a5b56.png", "format": "png", "width": 1000, "height": 812, "caption": "the webster mesh home office chairs are available in six colors"}, "reviewed": true, "_timestamp": 1716317439.583193, "_runtime": 1.7920711040496826, "_step": 0, "_wandb": {"runtime": 1}}