{"number": 9, "target": "yellow stars", "target_context": "a light blue ensign with the map of the island of nine yellow stars", "image_url": "https://thumbs.dreamstime.com/b/barcode-set-color-tuvalu-flag-light-blue-ensign-map-island-nine-yellow-stars-text-made-tuvalu-139420998.jpg", "dataset_name": "conceptual_12m-train", "org_id": 8470971, "image": {"_type": "image-file", "sha256": "2309b46dc39ea0c25d73355f4015a67b5f65366a2d87a28fa830b74ee4d38916", "size": 205904, "path": "media/images/image_0_2309b46dc39ea0c25d73.png", "format": "png", "width": 800, "height": 803, "caption": "a light blue ensign with the map of the island of nine yellow stars"}, "reviewed": true, "_timestamp": 1716412674.1617951, "_runtime": 2.5726702213287354, "_step": 0, "_wandb": {"runtime": 1}}