{"number": 10, "target": "Dinner Plates", "target_context": "Set of Ten Wedgwood Saint Paul's School Dinner Plates", "image_url": "https://dn9ml16rd2hb8.cloudfront.net/2023/02/65-4905-Set-of-Wedgwood-Plates-A-IMG_9272-540x345.jpg", "dataset_name": null, "org_id": null, "image": {"_type": "image-file", "sha256": "201657a9a5f1ac92aa3f9fd0d3f8b1f5116f099eb9bdf19fdba8174f6c56945d", "size": 365116, "path": "media/images/image_0_201657a9a5f1ac92aa3f.png", "format": "png", "width": 540, "height": 345, "caption": "Set of Ten Wedgwood Saint Paul's School Dinner Plates"}, "reviewed": true, "_timestamp": 1716739968.478749, "_runtime": 3.7887039184570312, "_step": 0, "_wandb": {"runtime": 2}}