{"number": 9, "target": "desktop flags", "target_context": "illustrations of nine desktop flags each of a country of the world", "image_url": "https://image.shutterstock.com/image-illustration/illustrations-desktop-flags-nine-countries-600w-71099629.jpg", "dataset_name": "conceptual_12m-train", "org_id": 11929515, "image": {"_type": "image-file", "sha256": "662696a27b085778ec5061e9ddb7e6086fa56780462312cc1562616666c69df4", "size": 186509, "path": "media/images/image_0_662696a27b085778ec50.png", "format": "png", "width": 428, "height": 620, "caption": "illustrations of nine desktop flags each of a country of the world"}, "reviewed": true, "_timestamp": 1716412470.956463, "_runtime": 2.3652431964874268, "_step": 0, "_wandb": {"runtime": 1}}